CNN4IE-0.1.9.dist-info/METADATA
CNN4IE-0.1.9.dist-info/RECORD
CNN4IE-0.1.9.dist-info/WHEEL
CNN4IE-0.1.9.dist-info/top_level.txt
CNN4IE-0.1.9.dist-info/zip-safe
cnn4ie/__init__.py
cnn4ie/attention_augmented_cnn/__init__.py
cnn4ie/attention_augmented_cnn/attn_aug_cnn.py
cnn4ie/attention_augmented_cnn/model.py
cnn4ie/attention_augmented_cnn/predict.py
cnn4ie/attention_augmented_cnn/train.py
cnn4ie/channel_spatial_attention_cnn/__init__.py
cnn4ie/channel_spatial_attention_cnn/channel_spatial_attention.py
cnn4ie/channel_spatial_attention_cnn/model.py
cnn4ie/channel_spatial_attention_cnn/predict.py
cnn4ie/channel_spatial_attention_cnn/train.py
cnn4ie/dcnn/__init__.py
cnn4ie/dcnn/dynamic_conv.py
cnn4ie/dcnn/model.py
cnn4ie/dcnn/predict.py
cnn4ie/dcnn/train.py
cnn4ie/dscnn/__init__.py
cnn4ie/dscnn/model.py
cnn4ie/dscnn/predict.py
cnn4ie/dscnn/train.py
cnn4ie/lambda_cnn/__init__.py
cnn4ie/lambda_cnn/lambda_cnn.py
cnn4ie/lambda_cnn/model.py
cnn4ie/lambda_cnn/predict.py
cnn4ie/lambda_cnn/train.py
cnn4ie/lcnn/__init__.py
cnn4ie/lcnn/lightweight_conv.py
cnn4ie/lcnn/model.py
cnn4ie/lcnn/predict.py
cnn4ie/lcnn/train.py
cnn4ie/mixed_attention_cnn/__init__.py
cnn4ie/mixed_attention_cnn/mixed_attention.py
cnn4ie/mixed_attention_cnn/model.py
cnn4ie/mixed_attention_cnn/predict.py
cnn4ie/mixed_attention_cnn/train.py
cnn4ie/mixed_depthwise_cnn/__init__.py
cnn4ie/mixed_depthwise_cnn/mixed_depthwise_cnn.py
cnn4ie/mixed_depthwise_cnn/model.py
cnn4ie/mixed_depthwise_cnn/predict.py
cnn4ie/mixed_depthwise_cnn/train.py
cnn4ie/mlrescnn/__init__.py
cnn4ie/mlrescnn/model.py
cnn4ie/mlrescnn/predict.py
cnn4ie/mlrescnn/train.py
cnn4ie/multi_cnn/__init__.py
cnn4ie/multi_cnn/model.py
cnn4ie/multi_cnn/multi_conv.py
cnn4ie/multi_cnn/predict.py
cnn4ie/multi_cnn/train.py
cnn4ie/self_attention_cnn/__init__.py
cnn4ie/self_attention_cnn/model.py
cnn4ie/self_attention_cnn/predict.py
cnn4ie/self_attention_cnn/self_attention_conv.py
cnn4ie/self_attention_cnn/train.py
cnn4ie/stand_alone_self_attention_cnn/__init__.py
cnn4ie/stand_alone_self_attention_cnn/model.py
cnn4ie/stand_alone_self_attention_cnn/predict.py
